README.rst
setup.py
ddbscan/__init__.py
ddbscan/ddbscan.py
ddbscan.egg-info/PKG-INFO
ddbscan.egg-info/SOURCES.txt
ddbscan.egg-info/dependency_links.txt
ddbscan.egg-info/requires.txt
ddbscan.egg-info/top_level.txt