Metadata-Version: 1.0
Name: ddbscan
Version: 0.2.0
Summary: Discrete DBSCAN algorithm optimized for discrete and bounded data.
Home-page: https://github.com/cloudwalkio/ddbscan
Author: Allan Inocencio de Souza Costa
Author-email: allan@cloudwalk.io
License: MIT
Platform: UNKNOWN
